CHANGES.txt
COPYRIGHT.txt
LICENSE.txt
README.txt
bootstrap.py
setup.py
src/z3c/__init__.py
src/z3c.recipe.winservice.egg-info/PKG-INFO
src/z3c.recipe.winservice.egg-info/SOURCES.txt
src/z3c.recipe.winservice.egg-info/dependency_links.txt
src/z3c.recipe.winservice.egg-info/entry_points.txt
src/z3c.recipe.winservice.egg-info/namespace_packages.txt
src/z3c.recipe.winservice.egg-info/requires.txt
src/z3c.recipe.winservice.egg-info/top_level.txt
src/z3c/recipe/__init__.py
src/z3c/recipe/winservice/README.txt
src/z3c/recipe/winservice/__init__.py
src/z3c/recipe/winservice/service.py
src/z3c/recipe/winservice/tests.py
src/z3c/recipe/winservice/winservice.in